easy_subscription/__init__.py
easy_subscription/admin.py
easy_subscription/conf.py
easy_subscription/fields.py
easy_subscription/forms.py
easy_subscription/models.py
easy_subscription/urls.py
easy_subscription/views.py
easy_subscription/integrations/__init__.py
easy_subscription/integrations/base.py
easy_subscription/integrations/hubspot.py
easy_subscription/locale/es/LC_MESSAGES/django.mo
easy_subscription/locale/es/LC_MESSAGES/django.po
easy_subscription/migrations/0001_initial.py
easy_subscription/migrations/__init__.py
easy_subscription/static/easy_subscription/css/subscription_form.css
easy_subscription/static/easy_subscription/js/subscription_form.js
easy_subscription/templates/easy_subscription/subscription_form.html
easy_subscription/templatetags/__init__.py
easy_subscription/templatetags/easy_subscription.py
django_easy_subscription-0.1.0.dist-info/LICENSE
django_easy_subscription-0.1.0.dist-info/METADATA
django_easy_subscription-0.1.0.dist-info/WHEEL
django_easy_subscription-0.1.0.dist-info/top_level.txt
django_easy_subscription-0.1.0.dist-info/RECORD
